aityping/__init__.py
aityping-0.0.1.dist-info/METADATA
aityping-0.0.1.dist-info/WHEEL
aityping-0.0.1.dist-info/top_level.txt
aityping-0.0.1.dist-info/RECORD
